setup.py
indi/__init__.py
indi.egg-info/PKG-INFO
indi.egg-info/SOURCES.txt
indi.egg-info/dependency_links.txt
indi.egg-info/requires.txt
indi.egg-info/top_level.txt