Metadata-Version: 1.0
Name: indi
Version: 0.0.1
Summary: Causal inference using model disentanglment.
Home-page: https://github.com
Author: Scott Lundberg
Author-email: scott.lundberg@microsoft.com
License: UNKNOWN
Platform: UNKNOWN
